[
  {
    "photourl": "https://randomuser.me/api/portraits/men/75.jpg",
    "ismain": true,
    "publicid": "pid754568769"
  },
  {
    "photourl": "https://randomuser.me/api/portraits/women/31.jpg",
    "ismain": true,
    "publicid": "pid288216202"
  },
  {
    "photourl": "https://randomuser.me/api/portraits/women/35.jpg",
    "ismain": true,
    "publicid": "pid811693770"
  },
  {
    "photourl": "https://randomuser.me/api/portraits/women/11.jpg",
    "ismain": true,
    "publicid": "pid555166464"
  },
  {
    "photourl": "https://randomuser.me/api/portraits/women/30.jpg",
    "ismain": true,
    "publicid": "pid591526788"
  },
  {
    "photourl": "https://randomuser.me/api/portraits/women/41.jpg",
    "ismain": true,
    "publicid": "pid334777477"
  },
  {
    "photourl": "https://randomuser.me/api/portraits/men/65.jpg",
    "ismain": true,
    "publicid": "pid481463497"
  },
  {
    "photourl": "https://randomuser.me/api/portraits/men/73.jpg",
    "ismain": true,
    "publicid": "pid254776478"
  },
  {
    "photourl": "https://randomuser.me/api/portraits/men/35.jpg",
    "ismain": true,
    "publicid": "pid317675500"
  },
  {
    "photourl": "https://randomuser.me/api/portraits/men/25.jpg",
    "ismain": true,
    "publicid": "pid671201207"
  },
  {
    "photourl": "https://randomuser.me/api/portraits/men/7.jpg",
    "ismain": true,
    "publicid": "pid761312497"
  },
  {
    "photourl": "https://randomuser.me/api/portraits/men/11.jpg",
    "ismain": true,
    "publicid": "pid798488973"
  },
  {
    "photourl": "https://randomuser.me/api/portraits/men/1.jpg",
    "ismain": true,
    "publicid": "pid635647285"
  },
  {
    "photourl": "https://randomuser.me/api/portraits/men/2.jpg",
    "ismain": true,
    "publicid": "pid442917519"
  },
  {
    "photourl": "https://randomuser.me/api/portraits/men/3.jpg",
    "ismain": true,
    "publicid": "pid346465638"
  },
  {
    "photourl": "https://randomuser.me/api/portraits/men/4.jpg",
    "ismain": true,
    "publicid": "pid869885334"
  },
  {
    "photourl": "https://randomuser.me/api/portraits/men/5.jpg",
    "ismain": true,
    "publicid": "pid448986134"
  },
  {
    "photourl": "https://randomuser.me/api/portraits/men/6.jpg",
    "ismain": true,
    "publicid": "pid814177465"
  },
  {
    "photourl": "https://randomuser.me/api/portraits/men/7.jpg",
    "ismain": true,
    "publicid": "pid142797901"
  },
  {
    "photourl": "https://randomuser.me/api/portraits/men/8.jpg",
    "ismain": true,
    "publicid": "pid590634771"
  },
  {
    "photourl": "https://randomuser.me/api/portraits/men/9.jpg",
    "ismain": true,
    "publicid": "pid703997357"
  },
  {
    "photourl": "https://randomuser.me/api/portraits/men/10.jpg",
    "ismain": true,
    "publicid": "pid320129976"
  },
  {
    "photourl": "https://randomuser.me/api/portraits/men/11.jpg",
    "ismain": true,
    "publicid": "pid701140812"
  },
  {
    "photourl": "https://randomuser.me/api/portraits/men/12.jpg",
    "ismain": true,
    "publicid": "pid429344552"
  },
  {
    "photourl": "https://randomuser.me/api/portraits/women/1.jpg",
    "ismain": true,
    "publicid": "pid477626020"
  },
  {
    "photourl": "https://randomuser.me/api/portraits/women/2.jpg",
    "ismain": true,
    "publicid": "pid542150556"
  },
  {
    "photourl": "https://randomuser.me/api/portraits/women/3.jpg",
    "ismain": true,
    "publicid": "pid253400113"
  },
  {
    "photourl": "https://randomuser.me/api/portraits/women/4.jpg",
    "ismain": true,
    "publicid": "pid417657552"
  },
  {
    "photourl": "https://randomuser.me/api/portraits/women/5.jpg",
    "ismain": true,
    "publicid": "pid446848605"
  },
  {
    "photourl": "https://randomuser.me/api/portraits/women/6.jpg",
    "ismain": true,
    "publicid": "pid839345542"
  }
]